LICENSE
sqlitedict/__init__.py
sqlitedict/py.typed
python_sqlitedict-0.0.3.dist-info/LICENSE
python_sqlitedict-0.0.3.dist-info/METADATA
python_sqlitedict-0.0.3.dist-info/WHEEL
python_sqlitedict-0.0.3.dist-info/RECORD
